Workbook

Sheet OIC input for DSR cal
A1: DSR & Stressed DSR - Basic information
A3: Borrower: | F3: Total gp exposure:
A4: Propose loan amount: | F4: Loan tenor:
A5: OIC: | F5: CA:
A6: Corp Type | B6: #1
A8: Where applicable, both cash flow forecast and debt-servicing ability should be conducted simultaneously when providing medium to long term facilities as below:-
A9: 1. Sydicated Loan, construction loan, term loan and mortgage loan with tenor > 1 year , including term loan under 內保外貸. For cashflow forecast, it should cover the whole period of loan life.
A11: Source of financial information:
A12: Historical DSR: | B12: Note | D12: Remarks:
A13: Type of statement: | B13: #2
A14: Latest Financial: | B14: #3 | D14: from: | F14: to:
A15: Full Year: | B15: #4
A16: Currency: | B16: #5
A18: Debt Financing: | C18: =C16 -> 0
A19: Existing Debt | B19: Note | C19: LN1 | D19: LN2 | E19: LN3 | F19: LN4 | G19: LN5 | H19: LN6 | I19: Sub-total | J19: Assumption & Justifications (please also marks your calculation):
A20: Existing LT Term Debt obligation | B20: #6 | I20: =SUM(C20:H20) -> 0
A21: Interest rate of Term Debt | B21: #7 | I21: =IF(I20=0,,(C20*C21+D20*D21+E20*E21+F20*F21+G20*G21+H20*H21)/I20) -> 0
A22: LT Term Loan principal repaid p.a. | B22: #6 | I22: =SUM(C22:H22) -> 0
A24: Bonds & Notes | B24: #8 | I24: =SUM(C24:H24) -> 0
A25: Interest Rate / Coupon rate | B25: #7 | I25: =IF(I24=0,,(C24*C25+D24*D25+E24*E25+F24*F25+G24*G25+H24*H25)/I24) -> 0
A26: Bonds & Notes maturing within 12 months | B26: #6 | I26: =SUM(C26:H26) -> 0
A28: ST / Revolving loan limit | B28: #6 | I28: =SUM(C28:H28) -> 0
A29: Interest rate of revolver | B29: #7 | I29: =IF(I28=0,,(C28*C29+D28*D29+E28*E29+F28*F29+G28*G29+H28*H29)/I28) -> 0
A32: New Debt
A33: Term Loan obligation | B33: #9 | I33: =SUM(C33:H33) -> 0
A34: Interest rate of Tern Loan | B34: #10 | I34: =IF(I33=0,,(C33*C34+D33*D34+E33*E34+F33*F34+G33*G34+H33*H34)/I33) -> 0
A35: Loan principal repaid p.a. | I35: =SUM(C35:H35) -> 0
A37: Bonds & Notes | B37: #9 | I37: =SUM(C37:H37) -> 0
A38: Interest Rate / Coupon rate | B38: #10 | I38: =IF(I37=0,,(C37*C38+D37*D38+E37*E38+F37*F38+G37*G38+H37*H38)/I37) -> 0
A40: ST / Revolving loan limit | B40: #9 | I40: =SUM(C40:H40) -> 0
A41: Interest rate of revolver | B41: #10 | I41: =IF(I40=0,,(C40*C41+D40*D41+E40*E41+F40*F41+G40*G41+H40*H41)/I40) -> 0
B44: Note | C44: Base case | D44: Stressed | E44: Assumption
A45: EBITDA | B45: #11 | D45: 0.1 | E45: discount on base EBITDA (ie 90% of base EBITDA)
A46: Add-on interest rate under stressed | B46: #12 | C46: NA | D46: 0.02
A48: #1: Input "0" for SME & Trading & "1" for Corporates & Manufacturing
A49: #2: Latest audited statement. Unaudited / draft statement are acceptable if the audited statements are not available.
A50: #3: Input latest financial year end ie 31 Dec 2022 & input financial period starts and end dates under remarks
A51: #4: Input "Y" for full year statement, otherwise, "N". For financial period covered not equal to 12 months, P&L for Latest AFS in the "OIC input for cash flow forecast" worksheet have to be adjusted manually to reflect annualised figures.
A52: #5: Currency should be the reported currency as per audited statements
A53: #6: OIC should try to obtain facilities letter or declaration from borrower on total GBF, interest rate & repayment schedule with other lenders. If information is available. input standalone LN obligation one by one or otherwise, aggregated loan obligation from latest audited F/S. All outstanding term debt (> than 1 year) and bonds including current portion long term debt and bonds, shall be input into respective item under “Existing Debt” section. Current portion long term debt disclosed in the financial statement or long term debt to be repaid within 12 months as per loan repayment schedule shall be input into “Term Loan Principal Repaid p.a.” and “Bonds & Notes maturing within 12 months” respectively. If there has been refinancing arrangement, revised repayment could only be input herewith with completed refinancing activities during the current financial year. Short term debt shall be input under ST Revolving loan section. Given the nature of revolving loan, one can assume all short term debt to be roll-over unless OIC has knowledge of banks exiting the banking relationship with the Borrower / Group. For mortgage installment loan, assumed principal repayment shall be after deduction of interest payment ie monthly installment x 12 mths - interest (current loan o/s x interest rate)
A54: #7: Input corresponding interest rate for each LN / Bond or weighted average interest rate for aggregated loan amount.
A55: #8: Input all the bonds issued or aggregate bond outstanding as per details disclosed in latest audited F/S.
A56: #9: Input proposed new debt by product type, ie term debt, Bond & notes or ST revolver. For syndicated / club loan, total facility amount (not just our portion) shall be input herewith
A57: #10: Input actual interest rate of the new debt
A58: #11. EBITDA = NP + int. + tax + depreciation + amort. of F.A. –/+ non-recurrent items. For volatile EBITDA over the last 3 financial years, weighted average EBITDA could be a substitute. For stress case, 10% discount on EBITDA (ie 90% of base EBITDA) will be the bank's basic requirement. OIC should provide justification if other than 10% discount on EBITDA under stressed case.
A59: #12: Interest rate of stressed DSR= existing interest rate +2% (as per latest guideline). OIC and CA could upward adjust the discount rate for stress case with justifications.
A61: =#REF! -> #REF!
A73: Audited
A74: Unaudited
A76: Y
A77: N
A79: 1 | B79: 0.01
A80: 0.95 | B80: 0.02
A81: 0.9 | B81: 0.03
A82: 0.85 | B82: 0.04
A83: 0.8 | B83: 0.05
A84: 0.75 | B84: 0.06
A85: 0.7 | B85: 0.07
A86: 0.65 | B86: 0.08
A87: 0.6 | B87: 0.09
A88: 0.55 | B88: 0.1
A89: 0.5 | B89: 0.11
A90: 0.45 | B90: 0.12
... A98: 0.05 | B98: 0.2
A100: 0
A101: 1

Sheet OIC input for cashflow
A1: OIC input basic information for cashflow forecast
A3: ='OIC input for DSR cal'!A3 -> Borrower: | C3: ='OIC input for DSR cal'!C3 -> 0 | G3: Period:
A4: ='OIC input for DSR cal'!A4 -> Propose loan amount: | C4: ='OIC input for DSR cal'!C4 -> 0 | G4: ='OIC input for DSR cal'!F3 -> Total gp exposure: | I4: ='OIC input for DSR cal'!H3 -> 0
A6: Basic Information:
A7: ='OIC input for DSR cal'!C16 -> 0 | D7: Note | E7: Latest AFS | F7: Yr 1 | G7: Yr. 2 | H7: Yr 3 | I7: Yr. 4 | J7: Yr. 5 | K7: Yr. 6 | L7: Yr. 7 | M7: Yr. 8 | N7: Yr. 9 | O7: Yr. 10 | P7: Yr. 11 | Q7: Yr. 12 | R7: Stressed | S7: Assumption
A8: FYE | E8: =+'OIC input for DSR cal'!C14 -> 0
A9: Sales & growth rate (%) in coming years | D9: #1 | R9: 0.1
A10: Current & forecast Gross Profit Margin ("GPM" in %) in coming years | D10: #2 | R10: 0
A11: Current & forecast Depreciation/Amortization charged to COGS (absolute amount) | D11: #3 | R11: NA
A12: Operating expenses in absolute amount (excluding depreciation & amortization) & growth rate (%) in coming years | D12: #4 | R12: NA
A13: Current & forecast Depreciation / Amortization (excluding charged in COGS) absolute amt in coming years | D13: #5 | R13: NA
A14: Investment/rental income & its absolute amt in coming years | D14: #6 | R14: NA
A15: of which non-cash investment income | D15: #6
A16: Share of contributions from associates or JV (P/L items) & its absolute amount in coming years | D16: #7 | R16: NA
A17: Dividend received from Associates or JV (absolute amt, from CF statement) & its absolute amt in the coming years | D17: #8
A18: Dividend receivable (B/S item) & its absolute amount in coming years | D18: #9 | R18: NA
A19: All other non-operating income & growth rate in coming years | D19: #10 | R19: NA
A20: All other non-operating expenditure & growth rate in coming years | D20: #11 | R20: NA
A21: Current & forecast Tax expense rate (% of pre-tax NP) in coming years | D21: #12 | R21: NA
A22: Current & forecast Dividends payout rate (% of NP) in coming years | D22: #13 | R22: NA
A23: Current & forecast Dividends payable (B/S item) absolute amt in coming years | D23: #14 | R23: NA
A24: Current & forecast Bad debt provision / exp (% of sales) in coming years | D24: #15 | R24: NA
A25: Debtors' t/o (days) | D25: #16 | R25: NA
A26: Debtors (absolute amt) | D26: #17 | F26: NA | G26: NA | H26: NA | I26: NA | J26: NA | K26: NA | L26: NA | M26: NA | N26: NA | O26: NA | P26: NA | Q26: NA | R26: NA
A27: Inventory t/o (days) | D27: #18 | R27: NA
A28: Inventory (absolute amt) | D28: #19 | F28: NA | G28: NA | H28: NA | I28: NA | J28: NA | K28: NA | L28: NA | M28: NA | N28: NA | O28: NA | P28: NA | Q28: NA | R28: NA
A29: Creditors' t/o (days) | D29: #20 | R29: NA
A30: Creditor (absolute amt) | D30: #21 | F30: NA | G30: NA | H30: NA | I30: NA | J30: NA | K30: NA | L30: NA | M30: NA | N30: NA | O30: NA | P30: NA | Q30: NA | R30: NA
A31: CAPEX (absolute amt) | D31: #22 | E31: NA | R31: 0
A32: Capex Financing Ratio | D32: #22 | R32: NA
A33: Estimated useful life of CAPEX (number of years) | D33: #23 | E33: NA | R33: NA
A34: Additional Depreciation for CAPEX (for Corp) | E34: NA | F34: =IF(OR('OIC input for DSR cal'!C6=0,F31=0,F33=0),0,F31/F33) -> 0 | G34: =IF(OR('OIC input for DSR cal'!C6=0,G31=0,G33=0),0,G31/G33) -> 0 | H34: =IF(OR('OIC input for DSR cal'!C6=0,H31=0,H33=0),0,H31/H33) -> 0 | I34: =IF(OR('OIC input for DSR cal'!C6=0,I31=0,I33=0),0,I31/I33) -> 0 | J34: =IF(OR('OIC input for DSR cal'!C6=0,J31=0,J33=0),0,J31/J33) -> 0 | K34: =IF(OR('OIC input for DSR cal'!C6=0,K31=0,K33=0),0,K31/K33) -> 0 | L34: =IF(OR('OIC input for DSR cal'!C6=0,L31=0,L33=0),0,L31/L33) -> 0 | M34: =IF(OR('OIC input for DSR cal'!C6=0,M31=0,M33=0),0,M31/M33) -> 0 | N34: =IF(OR('OIC input for DSR cal'!C6=0,N31=0,N33=0),0,N31/N33) -> 0 | O34: =IF(OR('OIC input for DSR cal'!C6=0,O31=0,O33=0),0,O31/O33) -> 0 | P34: =IF(OR('OIC input for DSR cal'!C6=0,P31=0,P33=0),0,P31/P33) -> 0 | Q34: =IF(OR('OIC input for DSR cal'!C6=0,Q31=0,Q33=0),0,Q31/Q33) -> 0 | R34: NA
A35: Additional Depreciation for CAPEX (for Corp - stressed) | E35: NA | F35: =IF(OR('OIC input for DSR cal'!$C$6=0,F31=0,F33=0),0,F31*(1-$R$31)/F33) -> 0 | G35: =IF(OR('OIC input for DSR cal'!$C$6=0,G31=0,G33=0),0,G31*(1-$R$31)/G33) -> 0 | H35: =IF(OR('OIC input for DSR cal'!$C$6=0,H31=0,H33=0),0,H31*(1-$R$31)/H33) -> 0 | I35: =IF(OR('OIC input for DSR cal'!$C$6=0,I31=0,I33=0),0,I31*(1-$R$31)/I33) -> 0 | J35: =IF(OR('OIC input for DSR cal'!$C$6=0,J31=0,J33=0),0,J31*(1-$R$31)/J33) -> 0 | K35: =IF(OR('OIC input for DSR cal'!$C$6=0,K31=0,K33=0),0,K31*(1-$R$31)/K33) -> 0 | L35: =IF(OR('OIC input for DSR cal'!$C$6=0,L31=0,L33=0),0,L31*(1-$R$31)/L33) -> 0 | M35: =IF(OR('OIC input for DSR cal'!$C$6=0,M31=0,M33=0),0,M31*(1-$R$31)/M33) -> 0 | ... Q35: =IF(OR('OIC input for DSR cal'!$C$6=0,Q31=0,Q33=0),0,Q31*(1-$R$31)/Q33) -> 0 | R35: NA
A36: Additional Depreciation for CAPEX (for SME / trading) | E36: NA | F36: =IF(OR('OIC input for DSR cal'!C6=1,F31=0,F33=0),0,F31/F33) -> 0 | G36: =IF(OR('OIC input for DSR cal'!C6=1,G31=0,G33=0),0,G31/G33) -> 0 | H36: =IF(OR('OIC input for DSR cal'!C6=1,H31=0,H33=0),0,H31/H33) -> 0 | I36: =IF(OR('OIC input for DSR cal'!C6=1,I31=0,I33=0),0,I31/I33) -> 0 | J36: =IF(OR('OIC input for DSR cal'!C6=1,J31=0,J33=0),0,J31/J33) -> 0 | K36: =IF(OR('OIC input for DSR cal'!C6=1,K31=0,K33=0),0,K31/K33) -> 0 | L36: =IF(OR('OIC input for DSR cal'!C6=1,L31=0,L33=0),0,L31/L33) -> 0 | M36: =IF(OR('OIC input for DSR cal'!C6=1,M31=0,M33=0),0,M31/M33) -> 0 | N36: =IF(OR('OIC input for DSR cal'!C6=1,N31=0,N33=0),0,N31/N33) -> 0 | O36: =IF(OR('OIC input for DSR cal'!C6=1,O31=0,O33=0),0,O31/O33) -> 0 | P36: =IF(OR('OIC input for DSR cal'!C6=1,P31=0,P33=0),0,P31/P33) -> 0 | Q36: =IF(OR('OIC input for DSR cal'!C6=1,Q31=0,Q33=0),0,Q31/Q33) -> 0 | R36: NA
A37: Additional Depreciation for CAPEX (for SME / trading - stressed) | E37: NA | F37: =IF(OR('OIC input for DSR cal'!$C$6=1,F31=0,F33=0),0,F31*(1-$R$31)/F33) -> 0 | G37: =IF(OR('OIC input for DSR cal'!$C$6=1,G31=0,G33=0),0,G31*(1-$R$31)/G33) -> 0 | H37: =IF(OR('OIC input for DSR cal'!$C$6=1,H31=0,H33=0),0,H31*(1-$R$31)/H33) -> 0 | I37: =IF(OR('OIC input for DSR cal'!$C$6=1,I31=0,I33=0),0,I31*(1-$R$31)/I33) -> 0 | J37: =IF(OR('OIC input for DSR cal'!$C$6=1,J31=0,J33=0),0,J31*(1-$R$31)/J33) -> 0 | K37: =IF(OR('OIC input for DSR cal'!$C$6=1,K31=0,K33=0),0,K31*(1-$R$31)/K33) -> 0 | L37: =IF(OR('OIC input for DSR cal'!$C$6=1,L31=0,L33=0),0,L31*(1-$R$31)/L33) -> 0 | M37: =IF(OR('OIC input for DSR cal'!$C$6=1,M31=0,M33=0),0,M31*(1-$R$31)/M33) -> 0 | ... Q37: =IF(OR('OIC input for DSR cal'!$C$6=1,Q31=0,Q33=0),0,Q31*(1-$R$31)/Q33) -> 0 | R37: NA
A38: Acquisition of investment (absolute amt, fm CF statement) | D38: #24 | R38: 0
A39: Proceeds of disposal of FA/investment (absolute amt, fm CF statement)) | D39: #25 | R39: NA
A40: all other current assets (absolute amt) in coming years | D40: #26 | R40: NA
A41: all other current liabilities (absolute amt) in coming years | D41: #27 | R41: NA
A42: interco claim (absolute amt) | D42: #28 | R42: NA
A43: interco debt (absolute amt) | D43: #29 | R43: NA
A44: all other long term assets (absolute amt) in coming years | D44: #30 | R44: NA
A45: all other long term liabilities (absolute amt) in coming years | D45: #31 | R45: NA
A46: Net Proceed of capital issue (absolute amt) in coming years | D46: #32 | E46: NA | R46: NA
A47: Proceed from new bond issue (absolute amt) in coming years | D47: #33 | E47: ='OIC input for DSR cal'!I37 -> 0 | R47: NA
A48: Bond Repayment | D48: #34
A49: Cash balance c/f | D49: #35 | F49: NA | G49: NA | H49: NA | I49: NA | J49: NA | K49: NA | L49: NA | M49: NA | N49: NA | O49: NA | P49: NA | Q49: NA | R49: NA
A50: New Debt (excluding Capex financing) | D50: #36 | E50: =+'OIC input for DSR cal'!I33+'OIC input for DSR cal'!I40 -> 0 | R50: NA
A51: New Debt - Capex Financing | D51: #37 | F51: =+F31*F32 -> 0 | G51: =+G31*G32 -> 0 | H51: =+H31*H32 -> 0 | I51: =+I31*I32 -> 0 | J51: =+J31*J32 -> 0 | K51: =+K31*K32 -> 0 | L51: =+L31*L32 -> 0 | M51: =+M31*M32 -> 0 | ... Q51: =+Q31*Q32 -> 0 | R51: NA
A52: Repayment of Capex Financing | D52: #38 | R52: NA
A53: Principal repayment of new debt (excluding Capex repayment) | D53: #39 | E53: NA | R53: NA
A54: Principal repayment - existing debt (absolute amt) | D54: #40 | E54: NA | R54: NA
A55: weighted avg. interest rate or the highest interest rate | D55: #41 | E55: =#REF! -> #REF! | R55: NA
A57: Working:
A58: Period | B58: ='OIC input for DSR cal'!C16 -> 0 | D58: Note | E58: Latest AFS | F58: Yr. 1 | G58: Yr. 2 | H58: Yr. 3 | I58: Yr. 4 | J58: Yr. 5 | K58: Yr. 6 | L58: Yr. 7 | M58: Yr. 8 | N58: Yr. 9 | O58: Yr. 10 | P58: Yr. 11 | Q58: Yr. 12 | R58: Assumption:
A59: debt b/f | E59: 0 | F59: =E67 -> 0 | G59: =F67 -> 0 | H59: =G67 -> 0 | I59: =H67 -> 0 | J59: =I67 -> 0 | K59: =J67 -> 0 | L59: =K67 -> 0 | M59: =L67 -> 0 | ... Q59: =P67 -> 0
A60: New debt | E60: 0 | F60: =E50+F50 -> 0 | G60: =G50 -> 0 | H60: =H50 -> 0 | I60: =I50 -> 0 | J60: =J50 -> 0 | K60: =K50 -> 0 | L60: =L50 -> 0 | M60: =M50 -> 0 | N60: =N50 -> 0 | ... Q60: =Q50 -> 0
A61: =+A51 -> New Debt - Capex Financing | E61: 0 | F61: =+F51 -> 0 | G61: =+G51 -> 0 | H61: =+H51 -> 0 | I61: =+I51 -> 0 | J61: =+J51 -> 0 | K61: =+K51 -> 0 | L61: =+L51 -> 0 | M61: =+M51 -> 0 | ... Q61: =+Q51 -> 0
A62: New Bond Issuance | E62: 0 | F62: =E47+F47 -> 0 | G62: =+G47 -> 0 | H62: =+H47 -> 0 | I62: =+I47 -> 0 | J62: =+J47 -> 0 | K62: =+K47 -> 0 | L62: =+L47 -> 0 | M62: =+M47 -> 0 | N62: =+N47 -> 0 | ... Q62: =+Q47 -> 0
A63: (Bond repayment) | E63: 0 | F63: =+F48 -> 0 | G63: =+G48 -> 0 | H63: =+H48 -> 0 | I63: =+I48 -> 0 | J63: =+J48 -> 0 | K63: =+K48 -> 0 | L63: =+L48 -> 0 | M63: =+M48 -> 0 | ... Q63: =+Q48 -> 0
A64: (Repayment of Capex Financing) | E64: 0 | F64: =F52 -> 0 | G64: =G52 -> 0 | H64: =H52 -> 0 | I64: =I52 -> 0 | J64: =J52 -> 0 | K64: =K52 -> 0 | L64: =L52 -> 0 | M64: =M52 -> 0 | ... Q64: =Q52 -> 0
A65: (Principal repayment of new debt) | E65: 0 | F65: =F53 -> 0 | G65: =G53 -> 0 | H65: =H53 -> 0 | I65: =I53 -> 0 | J65: =J53 -> 0 | K65: =K53 -> 0 | L65: =L53 -> 0 | M65: =M53 -> 0 | ... Q65: =Q53 -> 0
A66: (Principal repayment of existing debt) | E66: 0 | F66: =F54 -> 0 | G66: =G54 -> 0 | H66: =H54 -> 0 | I66: =I54 -> 0 | J66: =J54 -> 0 | K66: =K54 -> 0 | L66: =L54 -> 0 | M66: =M54 -> 0 | ... Q66: =Q54 -> 0
A67: debt c/f | D67: #42 | E67: ='OIC input for DSR cal'!I20+'OIC input for DSR cal'!I24+'OIC input for DSR cal'!I28 -> 0 | F67: =F59+F60+F61+F62-F63-F64-F65-F66 -> 0 | G67: =G59+G60+G61+G62-G63-G64-G65-G66 -> 0 | H67: =H59+H60+H61+H62-H63-H64-H65-H66 -> 0 | I67: =I59+I60+I61+I62-I63-I64-I65-I66 -> 0 | J67: =J59+J60+J61+J62-J63-J64-J65-J66 -> 0 | K67: =K59+K60+K61+K62-K63-K64-K65-K66 -> 0 | L67: =L59+L60+L61+L62-L63-L64-L65-L66 -> 0 | M67: =M59+M60+M61+M62-M63-M64-M65-M66 -> 0 | ... Q67: =Q59+Q60+Q61+Q62-Q63-Q64-Q65-Q66 -> 0
A68: Cpex Financing (stressed) | E68: 0 | F68: =+F51*(1-$R$31) -> 0 | G68: =+G51*(1-$R$31) -> 0 | H68: =+H51*(1-$R$31) -> 0 | I68: =+I51*(1-$R$31) -> 0 | J68: =+J51*(1-$R$31) -> 0 | K68: =+K51*(1-$R$31) -> 0 | L68: =+L51*(1-$R$31) -> 0 | M68: =+M51*(1-$R$31) -> 0 | ... Q68: =+Q51*(1-$R$31) -> 0
A69: (Repayment of Capex Financing - stressed) | E69: 0 | F69: =F52*(1-$R$31) -> 0 | G69: =G52*(1-$R$31) -> 0 | H69: =H52*(1-$R$31) -> 0 | I69: =I52*(1-$R$31) -> 0 | J69: =J52*(1-$R$31) -> 0 | K69: =K52*(1-$R$31) -> 0 | L69: =L52*(1-$R$31) -> 0 | M69: =M52*(1-$R$31) -> 0 | ... Q69: =Q52*(1-$R$31) -> 0
A70: debt c/f (stressed) | D70: #42 | E70: ='OIC input for DSR cal'!I20+'OIC input for DSR cal'!I24+'OIC input for DSR cal'!I28 -> 0 | F70: =F59+F60+F68+F62-F63-F65-F66-F69 -> 0 | G70: =G59+G60+G68+G62-G63-G65-G66-G69 -> 0 | H70: =H59+H60+H68+H62-H63-H65-H66-H69 -> 0 | I70: =I59+I60+I68+I62-I63-I65-I66-I69 -> 0 | J70: =J59+J60+J68+J62-J63-J65-J66-J69 -> 0 | K70: =K59+K60+K68+K62-K63-K65-K66-K69 -> 0 | L70: =L59+L60+L68+L62-L63-L65-L66-L69 -> 0 | M70: =M59+M60+M68+M62-M63-M65-M66-M69 -> 0 | ... Q70: =Q59+Q60+Q68+Q62-Q63-Q65-Q66-Q69 -> 0
A71: Interest paid under base case (Error if negative figure) | D71: #43 | E71: =#REF! -> #REF! | F71: =IF(F67<0,"Error",(F59+F67)/2*F55) -> 0 | G71: =IF(G67<0,"Error",(G59+G67)/2*G55) -> 0 | H71: =IF(H67<0,"Error",(H59+H67)/2*H55) -> 0 | I71: =IF(I67<0,"Error",(I59+I67)/2*I55) -> 0 | J71: =IF(J67<0,"Error",(J59+J67)/2*J55) -> 0 | K71: =IF(K67<0,"Error",(K59+K67)/2*K55) -> 0 | L71: =IF(L67<0,"Error",(L59+L67)/2*L55) -> 0 | M71: =IF(M67<0,"Error",(M59+M67)/2*M55) -> 0 | ... Q71: =IF(Q67<0,"Error",(Q59+Q67)/2*Q55) -> 0
A72: Interest paid under stressed case | D72: #43 | E72: NA | F72: =IF(F67<0,"Error",(F59+F70)/2*(F55+'OIC input for DSR cal'!$D$46)) -> 0 | G72: =IF(G67<0,"Error",(F70+G70)/2*(G55+'OIC input for DSR cal'!$D$46)) -> 0 | H72: =IF(H67<0,"Error",(G70+H70)/2*(H55+'OIC input for DSR cal'!$D$46)) -> 0 | I72: =IF(I67<0,"Error",(H70+I70)/2*(I55+'OIC input for DSR cal'!$D$46)) -> 0 | J72: =IF(J67<0,"Error",(I70+J70)/2*(J55+'OIC input for DSR cal'!$D$46)) -> 0 | K72: =IF(K67<0,"Error",(J70+K70)/2*(K55+'OIC input for DSR cal'!$D$46)) -> 0 | L72: =IF(L67<0,"Error",(K70+L70)/2*(L55+'OIC input for DSR cal'!$D$46)) -> 0 | M72: =IF(M67<0,"Error",(L70+M70)/2*(M55+'OIC input for DSR cal'!$D$46)) -> 0 | N72: =IF(N67<0,"Error",(M70+N70)/2*(N55+'OIC input for DSR cal'!$D$46)) -> 0 | ... Q72: =IF(Q67<0,"Error",(P70+Q70)/2*(Q55+'OIC input for DSR cal'!$D$46)) -> 0
A75: Supplementary Notes to OIC, please also refer to "Cash Flow Forecast Template Guide" for details
A76: OIC should provide the assumptions for the projection. Rationale and justification for all the assumption have to be duly documented under the "Assumption" column
A77: All forecast figures could be referred to last 3 years average if the figures are volatile or last year actual rate with stable uptrend or downtrend.
A78: #1: Sales referred to income generated from core business and shall refer to Turnover (Net sales) from the spreadsheets' PLinput. Sales growth rate shall make reference to histroical rates and trends while other factors that might affect the future sales shall also be considered.
A79: #2: Actual GPM shall refer to that of the spreadsheets. Projected GPM could be based on historical margin and trend. Any key factors that might have potential impact over GPM shall also be taken into account.
A80: #3: Depreciation charged to Cost of Goods Sold ("COGS") shall referred to Row 11 of the spreadsheets' PLinput. For production and manufacturing companies, signifcant depreciation would be charged to COGS. Future Depreciation could be assumed flat herewith as additional depreciaton would be calculated from the Capex.
A81: #4: Operating expenses (including selling and distribution expenses, staff expenses / fringe benefits, directors' remuneration, operating & admin expenses, rents and rates, R&D expenses and other expenses) shall be in absolute amount. Forecast shall be presented as a growth percentage (%) to the actual.
A82: #5: Depreciation charged to Operating Expenses shall referred to Row 34 of the spreadsheets' PLinput. In the case where no breakdown of depreciaton expenses provided, one shall decide the input in accordance to the Borrower / Group's business nature. Future Depreciation could be assumed flat herewith as additional depreciaton would be calculated from the Capex.
A83: #6: Investment/ rental income could be provided herewith. Only if recurrent income recorded for past 3 years, it could be applied for the projection. Situation where high volatility noticed,3-year weighted average or the least contribution over the past 3 FYs should be applied. If any non-cash investment income forming part of the investment / rental income record in former row (Row 14, deatils check breakdown in financial statement), the sum of non-cash investment income shall be recorded in "non-cash investment income" which is in Row 15 herewith
A84: #7: Input herewith shall take into consideration if the contribution is recurrent as well as the contribution trend. Any disposal or new associates / JV invested during the financial year that might impact the contribution to the group shall be considered.
A85: #8: The data shall be obtained from cash flow statement and projection in the coming years shall base on the recurrence of the dividend. 3-yr weighted average shall be considered if the dividend income is volatile.
A86: #9: Given dividend payment from associates / JV or investments would be subject to commercial decision, for simplicity, could assume staying flat or set to zero.
... A120: #43: Interest paid calculated based on average loan o/s. For stress case, add on interest rate will base on the input under "OIC input for DSR cal" worksheet.
A123: =#REF! -> #REF!
A135: percentage | C135: Days | D135: years
A136: -0.7 | B136: 1 | C136: 0 | D136: 0
A137: -0.65 | B137: 0.95 | C137: 5 | D137: 3
A138: -0.6 | B138: 0.9 | C138: 10 | D138: 4
A139: -0.55 | B139: 0.85 | C139: 15 | D139: 5
A140: -0.5 | B140: 0.8 | C140: 20 | D140: 6
A141: -0.45 | B141: 0.75 | C141: 25 | D141: 7
A142: -0.4 | B142: 0.7 | C142: 30 | D142: 8
A143: -0.35 | B143: 0.65 | C143: 35 | D143: 9
A144: -0.3 | B144: 0.6 | C144: 40 | D144: 10
A145: -0.25 | B145: 0.55 | C145: 45 | D145: 11
A146: -0.2 | B146: 0.5 | C146: 50 | D146: 12
A147: -0.19 | B147: 0.45 | C147: 55 | D147: 15
... A152: -0.14 | B152: 0.2 | C152: 80 | D152: 40
A153: -0.13 | B153: 0.15 | C153: 85
A154: -0.12 | B154: 0.1 | C154: 90
A155: -0.11 | B155: 0.05 | C155: 95
...
